mloptm/__init__.py
mloptm/consts.py
mloptm/exceptions.py
mloptm/grads.py
mloptm/methods.py
mloptm/utils.py
mloptm-1.0.8.dist-info/LICENSE.txt
mloptm-1.0.8.dist-info/METADATA
mloptm-1.0.8.dist-info/WHEEL
mloptm-1.0.8.dist-info/top_level.txt
mloptm-1.0.8.dist-info/RECORD
