Metadata-Version: 2.1
Name: mloptm
Version: 1.0.8
Summary: Implementation of ML Optimization Methods in Python
Home-page: https://github.com/moaz-elesawey/mloptm
Author: Moaz Mohammed El-Essawey
Author-email: mohammedmiaz3141@gmail.com
License: UNKNOWN
Project-URL: Source, https://github.com/moaz-elesawey/mloptm
Keywords: python,python3,ml,optm,mloptm
Platform: UNKNOWN
Classifier: Development Status :: 5 - Production/Stable
Classifier: Intended Audience :: Developers
Classifier: Topic :: Software Development :: Build Tools
Classifier: Programming Language :: Python :: 3
Classifier: Programming Language :: Python :: 3.6
Classifier: Programming Language :: Python :: 3.7
Classifier: Programming Language :: Python :: 3.8
Classifier: Programming Language :: Python :: 3.9
Classifier: Programming Language :: Python :: 3 :: Only
Classifier: License :: OSI Approved :: MIT License
Requires-Python: >=3.7, <4
License-File: LICENSE.txt
Requires-Dist: numpy
Requires-Dist: sympy
Requires-Dist: matplotlib
Requires-Dist: tabulate
Requires-Dist: Pillow
